pyopenjtalk_mod-0.4.1.post3.dist-info/RECORD
pyopenjtalk_mod-0.4.1.post3.dist-info/WHEEL
pyopenjtalk_mod-0.4.1.post3.dist-info/top_level.txt
pyopenjtalk_mod-0.4.1.post3.dist-info/METADATA
pyopenjtalk_mod-0.4.1.post3.dist-info/licenses/LICENSE.md
pyopenjtalk/version.py
pyopenjtalk/hougen.py
pyopenjtalk/openjtalk.cpython-310-darwin.so
pyopenjtalk/__init__.py
pyopenjtalk/types.py
pyopenjtalk/openjtalk.pyi
pyopenjtalk/utils.py
pyopenjtalk/py.typed
pyopenjtalk/htsengine.pyi
pyopenjtalk/htsengine.cpython-310-darwin.so
pyopenjtalk/__main__.py
pyopenjtalk/user_dictionary/katakana.dic
pyopenjtalk/user_dictionary/filler-jouyou.dic
pyopenjtalk/user_dictionary/sangokushi-name.dic
pyopenjtalk/user_dictionary/kanji_4_5gram_1.dic
pyopenjtalk/user_dictionary/kanji_4_5gram_0.dic
pyopenjtalk/user_dictionary/hiragana.dic
pyopenjtalk/user_dictionary/kanji_2gram.dic
pyopenjtalk/user_dictionary/chinese-person-name.dic
pyopenjtalk/user_dictionary/kanji_3gram_0.dic
pyopenjtalk/user_dictionary/kanji_3gram_1.dic
pyopenjtalk/user_dictionary/chinese-history-name.dic
pyopenjtalk/htsvoice/LICENSE_mei_normal.htsvoice
pyopenjtalk/htsvoice/mei_normal.htsvoice
pyopenjtalk/dictionary/rewrite.def
pyopenjtalk/dictionary/left-id.def
pyopenjtalk/dictionary/pos-id.def
pyopenjtalk/dictionary/matrix.bin
pyopenjtalk/dictionary/unk.dic
pyopenjtalk/dictionary/sys.dic
pyopenjtalk/dictionary/right-id.def
pyopenjtalk/dictionary/char.bin
pyopenjtalk/dictionary/COPYING
pyopenjtalk/yomi_model/nani_predict.py
pyopenjtalk/yomi_model/nani_enc.onnx
pyopenjtalk/yomi_model/convert_onnx.py
pyopenjtalk/yomi_model/nani_model.onnx
