Metadata-Version: 2.4
Name: pyopenjtalk-mod
Version: 0.4.1.post3
Summary: A Python wrapper for OpenJTalk with additional improvements
Home-page: https://github.com/WariHima/pyopenjtalk-mod
Author: Ryuichi Yamamoto
Author-email: zryuichi@gmail.com
License: MIT
Keywords: OpenJTalk,Research
Classifier: Operating System :: POSIX
Classifier: Operating System :: Unix
Classifier: Operating System :: MacOS
Classifier: Operating System :: Microsoft :: Windows
Classifier: Programming Language :: Cython
Classifier: Programming Language :: Python
Classifier: Programming Language :: Python :: 3
Classifier: Programming Language :: Python :: 3.9
Classifier: Programming Language :: Python :: 3.10
Classifier: Programming Language :: Python :: 3.11
Classifier: Programming Language :: Python :: 3.12
Classifier: Programming Language :: Python :: 3.13
Classifier: License :: OSI Approved :: MIT License
Classifier: Topic :: Scientific/Engineering
Classifier: Topic :: Software Development
Classifier: Intended Audience :: Science/Research
Classifier: Intended Audience :: Developers
License-File: LICENSE.md
Requires-Dist: importlib_resources; python_version < "3.9"
Requires-Dist: numpy>=1.24.0
Requires-Dist: sudachipy; python_version >= "3.9"
Requires-Dist: sudachipy<=0.6.8; python_version < "3.9"
Requires-Dist: sudachidict_core
Provides-Extra: docs
Requires-Dist: sphinx_rtd_theme; extra == "docs"
Requires-Dist: nbsphinx>=0.8.6; extra == "docs"
Requires-Dist: Jinja2>=3.0.1; extra == "docs"
Requires-Dist: pandoc; extra == "docs"
Requires-Dist: ipython; extra == "docs"
Requires-Dist: jupyter; extra == "docs"
Provides-Extra: dev
Requires-Dist: cython>=3.0; extra == "dev"
Requires-Dist: ruff; extra == "dev"
Requires-Dist: taskipy; extra == "dev"
Requires-Dist: types-setuptools; extra == "dev"
Requires-Dist: click; extra == "dev"
Requires-Dist: types-decorator; extra == "dev"
Requires-Dist: importlib-metadata<5.0; extra == "dev"
Provides-Extra: test
Requires-Dist: pytest; extra == "test"
Provides-Extra: onnxruntime
Requires-Dist: onnxruntime; extra == "onnxruntime"
Provides-Extra: marine
Requires-Dist: marine-plus; extra == "marine"
Dynamic: author
Dynamic: author-email
Dynamic: classifier
Dynamic: description
Dynamic: description-content-type
Dynamic: home-page
Dynamic: keywords
Dynamic: license
Dynamic: license-file
Dynamic: provides-extra
Dynamic: requires-dist
Dynamic: summary
